license.txt
setup.py
pro_video_toolsda/__init__.py
pro_video_toolsda/camera.py
pro_video_toolsda/video.py
pro_video_toolsda.egg-info/PKG-INFO
pro_video_toolsda.egg-info/SOURCES.txt
pro_video_toolsda.egg-info/dependency_links.txt
pro_video_toolsda.egg-info/top_level.txt