Metadata-Version: 2.1
Name: pro-video-toolsda
Version: 1.0
Summary: Este pacote fornece tools video processing
Author: Daniel Ramos
Author-email: danielramos@gmail.com
Keywords: camera,video,tools
License-File: license.txt
